plotextractor/__init__.py
plotextractor/api.py
plotextractor/config.py
plotextractor/converter.py
plotextractor/errors.py
plotextractor/extractor.py
plotextractor/output_utils.py
plotextractor-1.0.21.dist-info/LICENSE
plotextractor-1.0.21.dist-info/METADATA
plotextractor-1.0.21.dist-info/WHEEL
plotextractor-1.0.21.dist-info/top_level.txt
plotextractor-1.0.21.dist-info/RECORD
