Metadata-Version: 2.1
Name: plotextractor
Version: 1.0.21
Summary: Small library for extracting plots used in scholarly communication.
Home-page: https://github.com/inspirehep/plotextractor
Author: CERN
Author-email: admin@inspirehep.net
License: GPLv2
Keywords: plots figures extraction TeX LaTeX
Platform: any
Classifier: Intended Audience :: Developers
Classifier: License :: OSI Approved :: GNU General Public License v2 (GPLv2)
Classifier: Operating System :: OS Independent
Classifier: Topic :: Software Development :: Libraries :: Python Modules
Classifier: Programming Language :: Python
Classifier: Programming Language :: Python :: 2.7
Classifier: Programming Language :: Python :: 3
Classifier: Programming Language :: Python :: 3.6
Classifier: Programming Language :: Python :: 3.7
Classifier: Programming Language :: Python :: 3.8
Classifier: Programming Language :: Python :: 3.9
Classifier: Programming Language :: Python :: 3.10
Classifier: Programming Language :: Python :: 3.11
License-File: LICENSE
Requires-Dist: subprocess32>=3.2.6
Requires-Dist: python-magic
Requires-Dist: six>=1.7.2
Requires-Dist: pillow>=6.2.2
Requires-Dist: pdf2image==1.7.1
Requires-Dist: pylatexenc==2.10
Provides-Extra: tests
Requires-Dist: coverage>=4.0.0; extra == "tests"
Requires-Dist: pytest>=2.8.0; extra == "tests"
Requires-Dist: pytest-cov>=2.1.0; extra == "tests"
